issue_expander/__init__.py
issue_expander/__main__.py
issue_expander/expander.py
issue_expander-0.1.12.dist-info/LICENSE.txt
issue_expander-0.1.12.dist-info/METADATA
issue_expander-0.1.12.dist-info/WHEEL
issue_expander-0.1.12.dist-info/entry_points.txt
issue_expander-0.1.12.dist-info/top_level.txt
issue_expander-0.1.12.dist-info/RECORD
