Metadata-Version: 2.1
Name: issue-expander
Version: 0.1.12
Summary: Expand GitHub issue references into Markdown links
Author-email: Adam Wolf <adamwolf@feelslikeburning.com>
License: MIT
Project-URL: Homepage, https://www.github.com/adamwolf/issue-expander
Project-URL: Issues, https://www.github.com/adamwolf/issue-expander/issues
Project-URL: Source code, https://www.github.com/adamwolf/issue-expander
Classifier: Development Status :: 2 - Pre-Alpha
Classifier: Environment :: Console
Classifier: Natural Language :: English
Classifier: Operating System :: OS Independent
Classifier: Programming Language :: Python :: 3
Classifier: Programming Language :: Python :: 3.7
Classifier: Programming Language :: Python :: 3.8
Classifier: Programming Language :: Python :: 3.9
Classifier: Programming Language :: Python :: 3.10
Classifier: Programming Language :: Python :: 3.11
Classifier: License :: OSI Approved :: MIT License
Classifier: Topic :: Text Processing :: Markup :: Markdown
Classifier: Topic :: Utilities
Requires-Python: >=3.7
License-File: LICENSE.txt
Requires-Dist: Click
Requires-Dist: certifi
Provides-Extra: dev
Requires-Dist: tox ; extra == 'dev'
Requires-Dist: pre-commit ; extra == 'dev'
Requires-Dist: pytest ; extra == 'dev'
Requires-Dist: coverage[toml] ; extra == 'dev'
Requires-Dist: cogapp ; extra == 'dev'
Requires-Dist: scriv ; extra == 'dev'
